django_gyro/__init__.py
django_gyro/apps.py
django_gyro/core.py
django_gyro/exporters.py
django_gyro/importers.py
django_gyro/importing.py
django_gyro/sources.py
django_gyro/targets.py
django_gyro-0.3.4.dist-info/LICENSE
django_gyro-0.3.4.dist-info/METADATA
django_gyro-0.3.4.dist-info/WHEEL
django_gyro-0.3.4.dist-info/RECORD
