Metadata-Version: 2.1
Name: django-gyro
Version: 0.3.4
Summary: Django Gyro
Home-page: https://github.com/dev360/django-gyro
License: BSD-3-Clause
Keywords: django,gyro,data,import,export
Requires-Python: >=3.9
Classifier: Development Status :: 2 - Pre-Alpha
Classifier: Environment :: Web Environment
Classifier: Framework :: Django
Classifier: Intended Audience :: Developers
Classifier: License :: OSI Approved :: BSD License
Classifier: Operating System :: OS Independent
Classifier: Programming Language :: Python
Classifier: Programming Language :: Python :: 3
Classifier: Programming Language :: Python :: 3.9
Classifier: Programming Language :: Python :: 3.10
Classifier: Programming Language :: Python :: 3.11
Classifier: Programming Language :: Python :: 3.12
Classifier: Programming Language :: Python :: 3.13
Requires-Dist: django (>=3.2)
Requires-Dist: psycopg2-binary (>=2.9,<3.0)
Requires-Dist: tqdm (>=4.66,<5.0)
Project-URL: Repository, https://github.com/dev360/django-gyro
